smart_chunker/__init__.py
smart_chunker/chunker.py
smart_chunker/sentenizer.py
smart_chunker-0.0.2.dist-info/LICENSE
smart_chunker-0.0.2.dist-info/METADATA
smart_chunker-0.0.2.dist-info/WHEEL
smart_chunker-0.0.2.dist-info/top_level.txt
smart_chunker-0.0.2.dist-info/RECORD
